ykdraco.cpython-311-x86_64-linux-gnu.so
ykdraco-1.0.0.dist-info/WHEEL
ykdraco-1.0.0.dist-info/METADATA
ykdraco-1.0.0.dist-info/LICENSE
ykdraco-1.0.0.dist-info/top_level.txt
ykdraco-1.0.0.dist-info/RECORD
ykdraco-1.0.0.data/data/include/draco/draco_features.h
ykdraco-1.0.0.data/data/include/draco/compression/encode.h
ykdraco-1.0.0.data/data/include/draco/compression/decode.h
ykdraco-1.0.0.data/data/include/draco/compression/encode_base.h
ykdraco-1.0.0.data/data/include/draco/compression/expert_encode.h
ykdraco-1.0.0.data/data/include/draco/compression/draco_compression_options.h
ykdraco-1.0.0.data/data/include/draco/compression/entropy/rans_symbol_encoder.h
ykdraco-1.0.0.data/data/include/draco/compression/entropy/rans_symbol_decoder.h
ykdraco-1.0.0.data/data/include/draco/compression/entropy/symbol_decoding.h
ykdraco-1.0.0.data/data/include/draco/compression/entropy/ans.h
ykdraco-1.0.0.data/data/include/draco/compression/entropy/rans_symbol_coding.h
ykdraco-1.0.0.data/data/include/draco/compression/entropy/symbol_encoding.h
ykdraco-1.0.0.data/data/include/draco/compression/entropy/shannon_entropy.h
ykdraco-1.0.0.data/data/include/draco/compression/mesh/mesh_sequential_encoder.h
ykdraco-1.0.0.data/data/include/draco/compression/mesh/mesh_edgebreaker_encoder_impl_interface.h
ykdraco-1.0.0.data/data/include/draco/compression/mesh/mesh_edgebreaker_traversal_predictive_encoder.h
ykdraco-1.0.0.data/data/include/draco/compression/mesh/mesh_edgebreaker_shared.h
ykdraco-1.0.0.data/data/include/draco/compression/mesh/mesh_edgebreaker_decoder_impl_interface.h
ykdraco-1.0.0.data/data/include/draco/compression/mesh/mesh_edgebreaker_decoder.h
ykdraco-1.0.0.data/data/include/draco/compression/mesh/mesh_edgebreaker_traversal_valence_encoder.h
ykdraco-1.0.0.data/data/include/draco/compression/mesh/mesh_encoder.h
ykdraco-1.0.0.data/data/include/draco/compression/mesh/mesh_edgebreaker_encoder_impl.h
ykdraco-1.0.0.data/data/include/draco/compression/mesh/mesh_edgebreaker_traversal_decoder.h
ykdraco-1.0.0.data/data/include/draco/compression/mesh/mesh_edgebreaker_traversal_encoder.h
